taosdevopsutils/__init__.py
taosdevopsutils/config.py
taosdevopsutils/slack.py
taosdevopsutils/cli/__init__.py
taosdevopsutils/cli/main.py
tests/test_taosdevopsutils/__init__.py
tests/test_taosdevopsutils/test_slack.py
taosdevopsutils-1.3.1.dist-info/LICENSE
taosdevopsutils-1.3.1.dist-info/METADATA
taosdevopsutils-1.3.1.dist-info/WHEEL
taosdevopsutils-1.3.1.dist-info/entry_points.txt
taosdevopsutils-1.3.1.dist-info/top_level.txt
taosdevopsutils-1.3.1.dist-info/RECORD
