Metadata-Version: 2.1
Name: taosdevopsutils
Version: 1.3.1
Summary: Utility Functions for the Taos Devops team
Home-page: https://github.com/taosdevops/taos-devops-utils
Author: TAOS DevopsNow
License: UNKNOWN
Platform: UNKNOWN
Classifier: Programming Language :: Python :: 3
Classifier: License :: OSI Approved :: GNU General Public License v3 or later (GPLv3+)
Classifier: Operating System :: OS Independent
Requires-Dist: requests (~=2.22)
Requires-Dist: slackclient (~=2.2)
Requires-Dist: Click (~=7.0)
